itp_interface/__init__.py
itp_interface/agent/__init__.py
itp_interface/agent/simple_proof_agent.py
itp_interface/coq_ser_api/__init__.py
itp_interface/coq_ser_api/contexts.py
itp_interface/coq_ser_api/coq_agent.py
itp_interface/coq_ser_api/coq_backend.py
itp_interface/coq_ser_api/coq_util.py
itp_interface/coq_ser_api/example.py
itp_interface/coq_ser_api/lsp_backend.py
itp_interface/coq_ser_api/py.typed
itp_interface/coq_ser_api/serapi_backend.py
itp_interface/coq_ser_api/util.py
itp_interface/lean/__init__.py
itp_interface/lean/lean4_local_data_extraction_transform.py
itp_interface/lean/parsing_helpers.py
itp_interface/lean/simple_lean4_sync_executor.py
itp_interface/lean/tactic_parser.py
itp_interface/lean/tactic_parser/TacticParser.lean
itp_interface/lean/tactic_parser/lake-manifest.json
itp_interface/lean/tactic_parser/lakefile.toml
itp_interface/lean/tactic_parser/lean-toolchain
itp_interface/lean/tactic_parser/test_user_example.lean
itp_interface/lean/tactic_parser/TacticParser/Base64.lean
itp_interface/lean/tactic_parser/TacticParser/DependencyParser.lean
itp_interface/lean/tactic_parser/TacticParser/DependencyParserMain.lean
itp_interface/lean/tactic_parser/TacticParser/LineParser.lean
itp_interface/lean/tactic_parser/TacticParser/Main.lean
itp_interface/lean/tactic_parser/TacticParser/ProofExtractor.lean
itp_interface/lean/tactic_parser/TacticParser/SyntaxWalker.lean
itp_interface/lean/tactic_parser/TacticParser/TacticExtractorMain.lean
itp_interface/lean/tactic_parser/TacticParser/Types.lean
itp_interface/lean/tactic_parser/TacticParser/Example/complex.lean
itp_interface/lean/tactic_parser/TacticParser/Example/simple.lean
itp_interface/lean_server/__init__.py
itp_interface/lean_server/commands.py
itp_interface/lean_server/lean3_search_tool.py
itp_interface/lean_server/lean4_repl_interface.py
itp_interface/lean_server/lean4_utils.py
itp_interface/lean_server/lean_cmd_server.py
itp_interface/lean_server/lean_context.py
itp_interface-1.5.0.dist-info/METADATA
itp_interface-1.5.0.dist-info/WHEEL
itp_interface-1.5.0.dist-info/entry_points.txt
itp_interface-1.5.0.dist-info/licenses/LICENSE
itp_interface-1.5.0.dist-info/RECORD
