Metadata-Version: 2.4
Name: itp_interface
Version: 1.5.0
Summary: Generic interface for hooking up to any Interactive Theorem Prover (ITP) and collecting data for training ML models for AI in formal theorem proving.
Project-URL: Homepage, https://github.com/trishullab/itp-interface
Project-URL: Issues, https://github.com/trishullab/itp-interface/issues
Author-email: Amitayush Thakur <amitayush@utexas.edu>
License-File: LICENSE
Classifier: License :: OSI Approved :: MIT License
Classifier: Operating System :: POSIX :: Linux
Classifier: Programming Language :: Python :: 3
Requires-Python: >=3.9
Requires-Dist: dataclasses-json==0.5.7
Requires-Dist: editdistance==0.8.1
Requires-Dist: faiss-cpu>=1.6.1
Requires-Dist: filelock>=3.12.4
Requires-Dist: grpcio>=1.51.3; python_version < '3.14'
Requires-Dist: hydra-core>=1.0.0
Requires-Dist: jsonlines==4.0.0
Requires-Dist: mathlibtools==1.3.2
Requires-Dist: numpy>=1.24.0
Requires-Dist: omegaconf>=2.0.1
Requires-Dist: pampy==0.3.0
Requires-Dist: parglare==0.16.1
Requires-Dist: pexpect==4.8.0
Requires-Dist: protobuf==3.20.3; python_version < '3.14'
Requires-Dist: pydantic>=2.10.6
Requires-Dist: pylspclient==0.0.3
Requires-Dist: rank-bm25==0.2.2
Requires-Dist: ray>=2.50.0; python_version < '3.14'
Requires-Dist: regex==2023.10.3
Requires-Dist: sexpdata==1.0.0
Requires-Dist: soundfile==0.12.1
Requires-Dist: tqdm>=4.27
Requires-Dist: urllib3>=2.0.7
Requires-Dist: wget==3.2
Provides-Extra: app
Requires-Dist: networkx>=3.1; extra == 'app'
Requires-Dist: pandas>=2.0.0; extra == 'app'
Requires-Dist: plotly>=5.17.0; extra == 'app'
Requires-Dist: scipy>=1.16.0; extra == 'app'
Requires-Dist: streamlit>=1.28.0; extra == 'app'
